odoo/addons/purchase_origin_link_sale/README.rst
odoo/addons/purchase_origin_link_sale/__init__.py
odoo/addons/purchase_origin_link_sale/__manifest__.py
odoo/addons/purchase_origin_link_sale/i18n/purchase_origin_link_sale.pot
odoo/addons/purchase_origin_link_sale/models/__init__.py
odoo/addons/purchase_origin_link_sale/models/purchase.py
odoo/addons/purchase_origin_link_sale/readme/CONTRIBUTORS.rst
odoo/addons/purchase_origin_link_sale/readme/DESCRIPTION.rst
odoo/addons/purchase_origin_link_sale/static/description/icon.png
odoo/addons/purchase_origin_link_sale/static/description/index.html
odoo/addons/purchase_origin_link_sale/tests/__init__.py
odoo/addons/purchase_origin_link_sale/tests/test_purchase_origin_link_sale.py
odoo13_addon_purchase_origin_link_sale-13.0.1.0.1.dist-info/METADATA
odoo13_addon_purchase_origin_link_sale-13.0.1.0.1.dist-info/WHEEL
odoo13_addon_purchase_origin_link_sale-13.0.1.0.1.dist-info/top_level.txt
odoo13_addon_purchase_origin_link_sale-13.0.1.0.1.dist-info/RECORD
